LICENSE
README.md
setup.py
ezemailmxverifier/__init__.py
ezemailmxverifier/ezemailmxverifier.py
ezemailmxverifier/public_suffix_list.dat.gz
ezemailmxverifier.egg-info/PKG-INFO
ezemailmxverifier.egg-info/SOURCES.txt
ezemailmxverifier.egg-info/dependency_links.txt
ezemailmxverifier.egg-info/not-zip-safe
ezemailmxverifier.egg-info/top_level.txt
ezemailmxverifier/tests/db_test.txt
ezemailmxverifier/tests/db_test_long_timeout.txt
ezemailmxverifier/tests/verify_emails.py